pagebreaksip/__init__.py
pagebreaksip/pagebreak_magic.py
pagebreaksip/pagebreaks_ip.py
pagebreaksip-0.1.13.dist-info/METADATA
pagebreaksip-0.1.13.dist-info/WHEEL
pagebreaksip-0.1.13.dist-info/top_level.txt
pagebreaksip-0.1.13.dist-info/RECORD
